tiffany/__init__.py
tiffany/compat.py
tiffany/import_mapper.py
tiffany/monkeypil.py
tiffany/from-pil-py3/Image.py
tiffany/from-pil-py3/ImageColor.py
tiffany/from-pil-py3/ImageFile.py
tiffany/from-pil-py3/ImagePalette.py
tiffany/from-pil-py3/TiffImagePlugin.py
tiffany/from-pil-py3/TiffTags.py
tiffany/test/test_tiffany.py
tiffany/test/data/lzw_pon.tiff.txt
tiffany/test/data/multipage.tiff
tiffany/test/data/recipe_1.tiff
tiffany/test/data/recipe_2.tiff
tiffany/test/data/recipe_3.tiff
tiffany-0.6.7.dist-info/DESCRIPTION.rst
tiffany-0.6.7.dist-info/entry_points.txt
tiffany-0.6.7.dist-info/METADATA
tiffany-0.6.7.dist-info/metadata.json
tiffany-0.6.7.dist-info/RECORD
tiffany-0.6.7.dist-info/top_level.txt
tiffany-0.6.7.dist-info/WHEEL
