Metadata-Version: 2.0
Name: tiffany
Version: 0.6.7
Summary: Tiffany -- read/write/arrange any multi-page Tiff, any compression
Home-page: https://bitbucket.org/pydica/tiffany
Author: Christian Tismer
Author-email: tismer@stackless.com
License: PSF
Download-URL: https://bitbucket.org/pydica/tiffany/downloads
Keywords: tiff fax G3/G4 multi-page monkeypatch PIL pydica
Platform: UNKNOWN
Classifier: Programming Language :: Python
Classifier: Programming Language :: Python :: 2.6
Classifier: Programming Language :: Python :: 2.7
Classifier: Programming Language :: Python :: 3.2
Classifier: Programming Language :: Python :: 3.3
Classifier: Programming Language :: Python :: 3.4
Classifier: Development Status :: 5 - Production/Stable
Classifier: Environment :: X11 Applications :: Qt
Classifier: Environment :: Console
Classifier: Environment :: MacOS X
Classifier: Environment :: Win32 (MS Windows)
Classifier: Environment :: Other Environment
Classifier: License :: OSI Approved :: Python Software Foundation License
Classifier: Intended Audience :: End Users/Desktop
Classifier: Intended Audience :: Developers
Classifier: Natural Language :: English
Classifier: Topic :: Multimedia :: Graphics :: Capture :: Scanners
Classifier: Topic :: Multimedia :: Graphics :: Graphics Conversion
Classifier: Topic :: Other/Nonlisted Topic
Classifier: Topic :: Software Development :: Libraries :: Python Modules
Classifier: Topic :: Utilities
